{
	"version": "1.0.0",
	"renderType": "multisparrow",
	"offsets": [
		0,
		0
	],
	"danceEvery": 1,
	"scale": 1,
	"name": "Sphis Girlfriend",
	"cameraOffsets": [
		0,
		0
	],
	"flipX": false,
	"singTime": 8,
	"startingAnimation": "idle",
	"isPixel": false,
	"healthIcon": {
		"isPixel": false,
		"offsets": [
			0,
			0
		],
		"scale": 1,
		"id": "gf",
		"flipX": false
	},
	"assetPath": "characters/sgf/sgf-basic",
	"animations": [
		{
			"offsets": [
				0,
				0
			],
			"flipY": false,
			"frameRate": 24,
			"prefix": "sgf idle",
			"name": "idle",
			"looped": false,
			"flipX": false
		},
		{
			"flipY": false,
			"offsets": [
				65,
				5
			],
			"frameRate": 24,
			"assetPath": "characters/sgf/sgf-cheer",
			"prefix": "sgf cheer",
			"flipX": false,
			"looped": false,
			"name": "cheer"
		}
	]
}